CoreNLG/AddTag.py
CoreNLG/DocumentConstructors.py
CoreNLG/Errors.py
CoreNLG/FreeText.py
CoreNLG/Intensity.py
CoreNLG/IterElems.py
CoreNLG/NlgTools.py
CoreNLG/NoInterpret.py
CoreNLG/Number.py
CoreNLG/PredefObjects.py
CoreNLG/Quickstart.py
CoreNLG/Synonyms.py
CoreNLG/__init__.py
CoreNLG/decorators.py
CoreNLG/main.py
CoreNLG/tools.py
CoreNLG/resources/contraction.py
CoreNLG/resources/default_words.json
CoreNLG/resources/ponctuation.json
CoreNLG-2.2.0.dist-info/LICENSE
CoreNLG-2.2.0.dist-info/METADATA
CoreNLG-2.2.0.dist-info/WHEEL
CoreNLG-2.2.0.dist-info/top_level.txt
CoreNLG-2.2.0.dist-info/RECORD
