Metadata-Version: 2.1
Name: CoreNLG
Version: 2.2.0
Summary: UNKNOWN
Home-page: https://github.com/societe-generale/core-nlg.git
Author: Fabien Giely
License: Apache v2
Platform: UNKNOWN
Requires-Dist: lxml
